[
    {
        "name": "Smart automobile",
        "contact": "9742077633",
        "address": "23, KHB colony , Yelahanka, Bangalore - 560064, Behind Prakash theatre"
    },
    {
        "name": "Mohans Auto Parts",
        "contact": "+(91)-80-28462410, 23439137",
        "address": "No.3, B B Rd, Yelahanka, Bangalore - 560064"
    },
    {
        "name": " Navrang Hardware & Auto Accessories",
        "contact": "+(91)-80-28461054, 28566522",
        "address": "B B Road, Yelahanka, Bangalore - 560064"
    },
    {
        "name": " Eagle Automobiles",
        "contact": "+(91)-9886325470",
        "address": "B B Road, Yelahanka, Bangalore - 560064"
    },
    {
        "name": "Mandeep Motors",
        "contact": "+(91)-80-28462185",
        "address": "B B Road, Yelahanka, Bangalore - 560064"
    },
    {
        "name": "Shree Auto Spares",
        "contact": "+(91)-9342877627+(91)-80-41757245",
        "address": "Amrut Complex, B B Road, Yelahanka, Bangalore - 560064"
    },
    {
        "name": " HKGN Automobiles",
        "contact": "+(91)-9916204501, 9739754225",
        "address": "BB road, Yelahanka, Bangalore - 560064"
    },
    {
        "name": " Shakthi Automobiles",
        "contact": "+(91)-80-41756013",
        "address": "No. 2, Siddappa Building, B B Road, Yelahanka, Bangalore - 560064"
    },
    {
        "name": "New Bangalore Automobiles",
        "contact": "+(91)-9008762478",
        "address": "Yelahanka, Bangalore, B B Road, Yelahanka, Bangalore - 560064"
    },
    {
        "name": "Sri Devi Automobiles",
        "contact": "+(91)-9972394652+(91)-80-41218626",
        "address": "No.14/28, Padma Complex, B B Road, Gandhi Nagar, Yelahanka, Bangalore - 560064, Opposite To Ram Motors, Opp KTM Bike Showroom"
    },
    {
        "name": "Bangalore Motor Owners Consumers Coperative Soc",
        "contact": "+(91)-80-22960308+(91)-80-26612680",
        "address": "1350, 4th Main Gandhi Nagar, Yelahanka, Bangalore - 560064, Opposite Sri Ram Motors"
    },
    {
        "name": "Mahalaxmi Automobiles",
        "contact": "9845639972",
        "address": "No.275, Raitara Santhe Main Road, Jakur Road, Yelahanka, Bangalore - 560064"
    },
    {
        "name": " Mohans Auto Parts",
        "contact": "",
        "address": "No.3, B B Rd, Yelahanka, Bangalore - 560064, Opp.sbt & C"
    },
    {
        "name": "Nema Auto Spares",
        "contact": "",
        "address": "#61 Govindappa Garden, Shivannahalli Main Road, Jakkur Main Road, Yelahanka Old Town, Bangalore - 560064, Next to HP gas office"
    },
    {
        "name": " ESTEM AUTO SPARES",
        "contact": "-9686246603",
        "address": "#481/1 1st floor, Kogilu road, MARUTHI nagar above ICICI ATM YELAHANKA BANGALORE , kogilu road, Yelahanka Old Town, Bangalore - 560064, opp MUTHOOT fincorp"
    },
    {
        "name": "N R Automobiles",
        "contact": "-9880068314",
        "address": "B B Road, Khb Colony, Yelahanka, Bangalore - 560064"
    },
    {
        "name": " Dwaraka Enterprises",
        "contact": "-28920130",
        "address": "No.764/681, Airport Road, Yelahanka, Bangalore - 560064, Opposite To Standard Tiles, Near Police Station"
    },
    {
        "name": " SRI MANJUNATHA AUTOMOBILES",
        "contact": "-9916932985",
        "address": "Near NES Bus Stop, no 728, Doddaballapura Road, Bangalore, Doddaballapura Road, Bangalore, Yelahanka New Town, Bangalore - 560064, Near Seshadripuram College"
    },
    {
        "name": "Heena Service Centre",
        "contact": "+(91)-80-41756047, +(91)-9844169333",
        "address": "B B Road, Yelahanka, Bangalore - 560064, Opp Standard Tiles Factory"
    },
    {
        "name": " KGN Under Charce Engineering Works",
        "contact": "+(91)-9900102876, 9902836785",
        "address": "B B Road, Yelahanka, Bangalore - 560064, Near Karnataka Service Station"
    },
    {
        "name": "Bhagyalakshmi Automobiles",
        "contact": "(91)-80-39558484",
        "address": "No.1334, East Sanitary Core, 16th Main, 3rd Phase, Yelahanka New Town, Bangalore - 560064, Near Kanthi Sweets! Near To Chikkbomsandra Cross"
    },
    {
        "name": "Federal Mogul Goetze India Ltd (Distribution Office)",
        "contact": "+(91)-8970650393, 8970650394, 8970650390, 8970650313",
        "address": "Doddaballapur Road, Yelahanka New Town, Bangalore - 560064, Opposite Sheshadripuram College"
    },
    {
        "name": "t Sai Automobiles",
        "contact": "",
        "address": "1871/1 & 2, Ground Floor, 11th B Main Road, 3rd Stage, Yelahanka New Town, Bangalore - 560064, Near hanuman Temple"
    },
    {
        "name": "Ambika Automobiles",
        "contact": "-7829810917",
        "address": "#1931, 9th B cross, Yelahanka New Town, Bangalore - 560064, Near Anjaneya Temple "
    },
    {
        "name": "S K Automobiles",
        "contact": "-9900113444",
        "address": "AMG Service Station, B B Road, Yelahanka, Bangalore - 560064, Next To Kendriya Vihar Apartments View Map"
    },
    {
        "name": "S K Auto Mobiles",
        "contact": "+(91)-9342562296",
        "address": "No.2129, MIG, 3rd STG, Bus Stand Mn Rd, Yelahanka New Town, Bangalore - 560064"
    },
    {
        "name": "Sri Ram Auto Works",
        "contact": "-9886374617",
        "address": "#38/7, MIG-D-707, 4th phase, Yelahanka New Town, Bangalore - 560064, Near Akshaya Daba"
    },
    {
        "name": "Raghavendra Services",
        "contact": "+(91)-9448713434, 9341295797",
        "address": "No B 80, Sri Bhavani Nilaya, 4t Cross, B Sector, Yelahanka, Bangalore - 560064"
    },
    {
        "name": "Krishna Automobile",
        "contact": "-9739216090",
        "address": "No.1, 2nd Main, Vinayaka Nagar, Bugler Main Road, Yelahanka, Bangalore - 560064, Near Nitesh Aparment"
    },
    {
        "name": " RAM AUTOMOBILES",
        "contact": "+(91)-80-33491933",
        "address": "#8, KOGILU MAIN ROAD, SRINIVASAPURA, Yelahanka, Bangalore - 560064, NEAR SHANIMAHATHMA TEMPLE"
    },
    {
        "name": "Softec Precision Products",
        "contact": "+(91)-80-55346441",
        "address": "C1a, Ist Cross, Kiadb Area, Yelahanka New Town, Bangalore - 560064, Yelahanka New Town"
    },
    {
        "name": " Syed Automobiles",
        "contact": "-8050691685",
        "address": "No.01, Ballali Cross Road, Yelahanka, Bangalore - 560064, Near Shamsu School"
    },
    {
        "name": "SN Automobiles & Agencies",
        "contact": "-9731829455",
        "address": "No.10, Yelhanka Road, Kogilu Cross, Bangalore - 560064, Near Annapoorneshwari temple"
    },
    {
        "name": " Maruthi Automobiles",
        "contact": "-9060360591",
        "address": "Doddaballapur Road, Rajanakunte, Bangalore - 560064, Rajanukunte"
    },
    {
        "name": "Ashapura Automobiles",
        "contact": "+(91)-9738945498, 9035173658",
        "address": "No 3, Bombay complex, Srirampura main road, Amruthahalli, Bangalore - 560064, Near old amruthahalli police station"
    },
    {
        "name": "MN AUTOMOBILES",
        "contact": "-8867173698",
        "address": "#155/55p/3, BELLAHLLI main road kogilu layout next to bridge north, kogilu main road, Kogilu Cross, Bangalore - 560064, near shams school"
    },
    {
        "name": "Savin CNC Engineering",
        "contact": "+(91)-80-7826227",
        "address": "Plot No.4/A, 2nd PH,Jigni Indl Area, Jigani, Bangalore - 560106"
    },
    {
        "name": " Saraswathi Helmet Palace",
        "contact": "+(91)-7795698742, 8904989146",
        "address": "No.29, Airport Road, Sahakara Nagar, Bangalore - 560092, Near Indian Oil Petrol Bunk"
    },
    {
        "name": " Sridhar Automobiles",
        "contact": "-9900817099",
        "address": "No 52, Jakkur Main Road,Amruthhalli, Byataranyanapura, Bangalore - 560092, Byatarayanapura"
    },
    {
        "name": "S.M.Battery House ",
        "contact": "9449173031 / 9738365363",
        "address": "#227 narsipura layout vidyaranyapura ban-97"
    },
    {
        "name": "Ashupra automobiles",
        "contact": "7204134559",
        "address": "#1991,1st main road , narsipura layout vidyaranyapura ban-97"
    },
    {
        "name": "Classic Motors",
        "contact": "080-41610192 / 9844179596 / 9019424187",
        "address": "#139 ,vidyaranyapura last us stop,ban-97"
    },
    {
        "name": "RNS  Motors LTD",
        "contact": "9538965835",
        "address": "D.B.Sandraarch opp to surya bakery,vidyaranyapura main road ban-97"
    }
]