[
    {
        "name": "R.K Digital studio",
        "contact": "9880138645",
        "address": "#43 opp to TVS shoroom near last bus stop vidyaranyapura last bus stop ban -97"
    },
    {
        "name": "Angeera studio",
        "contact": "9731888368",
        "address": "367/B, 3rd crosss,9th main nti layout vidyaranyapura,ban-97"
    },
    {
        "name": "Photo junction",
        "contact": "+(91)-80-23642096, +(91)-9663526643",
        "address": "#4-138/5, Bel Layout., Vidyaranyapura Block 1, Below Benaka Sweets, Bangalore - 560097"
    },
    {
        "name": "R K Color Lab & Studio ",
        "contact": "+(91)-9880138645",
        "address": "No.43, Vidyaranyapura, Near Bus Stand, Opposite TVS Showroom, Bangalore - 560097"
    },
    {
        "name": "Konica digital studio",
        "contact": "+(91)-9945594820, 9060698391",
        "address": "#110/2, Doddabommasandra, Vidyaranyapura, Near government school, Bangalore - 560097"
    },
    {
        "name": "Sree Digital Creator",
        "contact": "+(91)-9035863262",
        "address": "No.44, Surabi Building, Ground Floor, 4th Cross, Vidyaranyapura, Near To Last Bus Stop, Bangalore - 560097"
    },
    {
        "name": "New Image Studio ",
        "contact": "+(91)-80-30586240, +(91)-9060227085",
        "address": "Ramachandrapuram, Vidyaranyapura, Opposite Manjunatha Studio, Bangalore - 560097"
    }
]