[
    {
        "name": "Mount Litera Zee School",
        "contact": "8066499051",
        "address": "No 9 1st main Ramanna garden vidaranyapura bangalore 560097"
    },
    {
        "name": "Podar Jumbo Kids plus",
        "contact": "08023646835/8884823939",
        "address": "No. 228 near vidya ganapathytemple NTI layout 8th A main vidyaranyapura bangalore-560097"
    },
    {
        "name": "Narayana E techno school ",
        "contact": "8722260955",
        "address": "Sapthagiri layout thindlu vidyaranyapura post bangalore-560097"
    },
    {
        "name": "Vyasa Interational School",
        "contact": "8023454777/9741055990",
        "address": "No. 101/2 near Bel north gate dodda bommasandra vidyaranyapura bangalore-560097"
    },
    {
        "name": "Sri Ravi Shankar Vidya mandir",
        "contact": "08023641305/9986075219",
        "address": "No. 4 HMT , Hbcs layout thindlu vidyaranyapura Bangalore-560097"
    },
    {
        "name": "MES Kishore kendra public school",
        "contact": "08023641565/23641567",
        "address": "3rd stage 4th main 11th cross vidyaranyapura bangalore-560097"
    },
    {
        "name": "EORU Kids",
        "contact": "8066497477",
        "address": "No. 802 near café coffee day 7th cross 7th main 4th block bel layout vidyaranyapura bangalore-560097"
    },
    {
        "name": "Busy Brains",
        "contact": "9036021560",
        "address": "No. 43/43 A near aswathkatte temple(near nagamma temple), 2nd main 3rd cross chamundeshwari layout vidyaranyapura bangalore-560097"
    },
    {
        "name": "Vyasa International School ",
        "contact": "(91)-80-23454777, +(91)-9741055990",
        "address": "No.101/2, Dodda Bommasandra, Vidyaranyapura, Nr Bel North Gate, Bangalore - 560097 "
    },
    {
        "name": "Kidzee",
        "contact": "(91)-80-66491473",
        "address": "No.7 3rdCrs SAINgr Vidyaranyapura NrSambramCollege Bangalore-560097"
    },
    {
        "name": "LittleElly",
        "contact": "(91)-9986052233, 9986074348",
        "address": "No.22,Vriksha,RamachandrapuraMainRoad,Vidyaranyapura,NearMountLiteraSchool,Bangalore-560097"
    },
    {
        "name": "DevaMathaCentralSchool",
        "contact": "(91)-80-23643752,65478145",
        "address": "DefenceLayout,Vidyaranyapura,Bangalore-560097"
    },
    {
        "name": "ST.Philomena'sEnglishSchool",
        "contact": "08023456443/41636086/23455794",
        "address": "#3, HMTLayout,behindBSNLoffice,vidyaranyapuraban-97"
    },
    {
        "name": "Montessoriteachertrainingcourse",
        "contact": "9845133608",
        "address": "C/OBeehiveplayschool,BELLayout,vidyaranyapura,ban-97"
    },
    {
        "name": "DEV-INNationalschool",
        "contact": "8065651001",
        "address": "#3/1,kodigehallimainroad,nexttocaverycollege,sahakarnagarban-97"
    },
    {
        "name": "ChetanaPUCollege",
        "contact": "18004194109",
        "address": "no295thphaseKHBcolonyyelahankanewtownbangalore64"
    },
    {
        "name": "Greencountrykindergarden",
        "contact": "9482480397",
        "address": "414-106/7ballaryroadnexttoIocpetrolbunkbangalore92"
    },
    {
        "name": "L.E.T.Cpvtltd",
        "contact": "080-32471288/23453597/9342580693",
        "address": "no6kalathurbuildinggangammacirclebangalore13"
    },
    {
        "name": "TheRegencyPublicSchool",
        "contact": "08023642370",
        "address": "No5/1AMSlayoutextensionvidyaranyapurabangalore560097"
    },
    {
        "name": "OrientalEnglishHighSchool",
        "contact": "08023641762",
        "address": "AMSLayout,Vidyaranyapura,Bengaluru,Karnataka560097"
    },
    {
        "name": "LittleMillennium",
        "contact": "9845014738",
        "address": " Swathi,No.58,1stBlock, 10thMain,2ndCross,NTILayout,Vidyaranyapura,Bengaluru,Karnataka560097"
    },
    {
        "name": "LittleLillysEnglishPublicSchool",
        "contact": "08033056978",
        "address": "8thMainRd,BELLayout4thBlock,Vidyaranyapura,Bengaluru, Karnataka560097"
    },
    {
        "name": "HELLOKIDS",
        "contact": "9986378453",
        "address": "979,2ndBlockBELLayout,BehindCanaraBank,Bengaluru,Karnataka560097"
    },
    {
        "name": "StPhilomenasSchool",
        "contact": "08023456443",
        "address": "VidyaranyapuraMainRoad,Near-PetrolBank, Doddabommasandra, Bengaluru,Karnataka560097"
    },
    {
        "name": "EKAAKSHARA-PLAYSCHOOL&DAYCAREIN ",
        "contact": "09901805305",
        "address": "143,3rd'A'Main6thBlock,NearVidyaranyapuraBusStop,Vidyaranyapura,Bengaluru,Karnataka560097"
    },
    {
        "name": "RajarajeshwariHighSchool",
        "contact": "08023455522",
        "address": "DoddaBommasandra,Vidyaranyapura, Bengaluru,Karnataka560097"
    },
    {
        "name": "NavodayaEducation&DevelopmentTrust",
        "contact": "08023457629",
        "address": " SriBaradarajasuuamyLayout, Sinagapura,NearM.SPalyaCircle,Vidyaranyapura,Bengaluru,Karnataka560097"
    },
    {
        "name": "SriChaitanyaTechnoSchool",
        "contact": "9900023922",
        "address": "#13/1,BesideAmbaBhavaniTemple,Doddabettahalli,Road,Vidyaranyapura,Bengaluru,Karnataka560097"
    },
    {
        "name": "VidyaSpoorthi",
        "contact": "08023645524",
        "address": " KempeGowdaNagar,Bengaluru,Karnataka560097"
    }
]